cock.py
cock-0.11.0.dist-info/METADATA
cock-0.11.0.dist-info/WHEEL
cock-0.11.0.dist-info/license.txt
cock-0.11.0.dist-info/top_level.txt
cock-0.11.0.dist-info/RECORD
