Metadata-Version: 2.1
Name: cock
Version: 0.11.0
Summary: configuration with click builder
Home-page: https://github.com/pohmelie/cock
Author: pohmelie
Author-email: multisosnooley@gmail.com
License: MIT
Classifier: Programming Language :: Python
Classifier: Programming Language :: Python :: 3
Requires-Python: >=3.7
License-File: license.txt
Requires-Dist: click (>=7.1.0)
Requires-Dist: sortedcontainers (>=2.3.0)
Requires-Dist: pyyaml (>=5.0.0)
Provides-Extra: dev
Requires-Dist: pytest ; extra == 'dev'
Requires-Dist: pytest-cov ; extra == 'dev'
Requires-Dist: flake8 ; extra == 'dev'
